Metadata-Version: 2.1
Name: mpqhsi
Version: 0.0.8
Summary: hsi for MPQ_code
Home-page: https://github.com/miaopeiqi
Author: MPQ
Author-email: miaopeiqi@163.com
License: UNKNOWN
Platform: UNKNOWN
